lyrics_transcriber/__init__.py
lyrics_transcriber/cli/__init__.py
lyrics_transcriber/cli/cli_main.py
lyrics_transcriber/core/__init__.py
lyrics_transcriber/core/config.py
lyrics_transcriber/core/controller.py
lyrics_transcriber/correction/agentic/__init__.py
lyrics_transcriber/correction/agentic/adapter.py
lyrics_transcriber/correction/agentic/agent.py
lyrics_transcriber/correction/agentic/feedback/aggregator.py
lyrics_transcriber/correction/agentic/feedback/collector.py
lyrics_transcriber/correction/agentic/feedback/retention.py
lyrics_transcriber/correction/agentic/feedback/store.py
lyrics_transcriber/correction/agentic/handlers/__init__.py
lyrics_transcriber/correction/agentic/handlers/ambiguous.py
lyrics_transcriber/correction/agentic/handlers/background_vocals.py
lyrics_transcriber/correction/agentic/handlers/base.py
lyrics_transcriber/correction/agentic/handlers/complex_multi_error.py
lyrics_transcriber/correction/agentic/handlers/extra_words.py
lyrics_transcriber/correction/agentic/handlers/no_error.py
lyrics_transcriber/correction/agentic/handlers/punctuation.py
lyrics_transcriber/correction/agentic/handlers/registry.py
lyrics_transcriber/correction/agentic/handlers/repeated_section.py
lyrics_transcriber/correction/agentic/handlers/sound_alike.py
lyrics_transcriber/correction/agentic/models/__init__.py
lyrics_transcriber/correction/agentic/models/ai_correction.py
lyrics_transcriber/correction/agentic/models/correction_session.py
lyrics_transcriber/correction/agentic/models/enums.py
lyrics_transcriber/correction/agentic/models/human_feedback.py
lyrics_transcriber/correction/agentic/models/learning_data.py
lyrics_transcriber/correction/agentic/models/observability_metrics.py
lyrics_transcriber/correction/agentic/models/schemas.py
lyrics_transcriber/correction/agentic/models/utils.py
lyrics_transcriber/correction/agentic/observability/__init__.py
lyrics_transcriber/correction/agentic/observability/langfuse_integration.py
lyrics_transcriber-0.81.0.dist-info/METADATA
lyrics_transcriber-0.81.0.dist-info/WHEEL
lyrics_transcriber-0.81.0.dist-info/entry_points.txt
lyrics_transcriber-0.81.0.dist-info/licenses/LICENSE
lyrics_transcriber-0.81.0.dist-info/RECORD
