Metadata-Version: 2.4
Name: lyrics-transcriber
Version: 0.81.0
Summary: Automatically create synchronised lyrics files in ASS and MidiCo LRC formats with word-level timestamps, using Whisper and lyrics from Genius and Spotify
License: MIT
License-File: LICENSE
Author: Andrew Beveridge
Author-email: andrew@beveridge.uk
Requires-Python: >=3.10,<3.14
Classifier: License :: OSI Approved :: MIT License
Classifier: Programming Language :: Python :: 3
Classifier: Programming Language :: Python :: 3.10
Classifier: Programming Language :: Python :: 3.11
Classifier: Programming Language :: Python :: 3.12
Classifier: Programming Language :: Python :: 3.13
Requires-Dist: attrs (>=23.0.0)
Requires-Dist: cattrs (>=23.0.0)
Requires-Dist: dropbox (>=12)
Requires-Dist: fastapi (>=0.115)
Requires-Dist: ffmpeg-python (>=0.2.0)
Requires-Dist: fonttools (>=4.55)
Requires-Dist: jiwer (>=3.0.0)
Requires-Dist: karaoke-lyrics-processor (>=0.6)
Requires-Dist: langchain (>=0.3.0)
Requires-Dist: langchain-anthropic (>=0.2.0)
Requires-Dist: langchain-core (>=0.3.0)
Requires-Dist: langchain-ollama (>=0.2.0)
Requires-Dist: langchain-openai (>=0.2.0)
Requires-Dist: langfuse (>=3.0.0)
Requires-Dist: langgraph (>=0.2.0)
Requires-Dist: lyricsgenius (>=0.1.0)
Requires-Dist: metaphone (>=0.6)
Requires-Dist: nltk (>=3.9)
Requires-Dist: ollama (>=0.4.7)
Requires-Dist: openai (>=1.63.2)
Requires-Dist: pillow (>=10.0.0)
Requires-Dist: pydantic (>=2.7.0)
Requires-Dist: pydub (>=0.25)
Requires-Dist: python-dotenv (>=1)
Requires-Dist: python-levenshtein (>=0.26)
Requires-Dist: python-slugify (>=8)
Requires-Dist: shortuuid (>=1.0.13)
Requires-Dist: spacy (>=3.8.7)
Requires-Dist: spacy-syllables (>=3)
Requires-Dist: srsly (>=2.5.1)
Requires-Dist: syllables (>=1)
Requires-Dist: syrics (>=0)
Requires-Dist: toml (>=0.10.0)
Requires-Dist: torch (>=2.7,<3.0)
Requires-Dist: tqdm (>=4.67)
Requires-Dist: transformers (>=4.47)
Requires-Dist: uvicorn (>=0.34)
Project-URL: Documentation, https://github.com/nomadkaraoke/python-lyrics-transcriber/blob/main/README.md
Project-URL: Homepage, https://github.com/nomadkaraoke/python-lyrics-transcriber
Project-URL: Repository, https://github.com/nomadkaraoke/python-lyrics-transcriber
